README.txt
setup.cfg
setup.py
collective/__init__.py
collective.ploneseltest.egg-info/PKG-INFO
collective.ploneseltest.egg-info/SOURCES.txt
collective.ploneseltest.egg-info/dependency_links.txt
collective.ploneseltest.egg-info/entry_points.txt
collective.ploneseltest.egg-info/namespace_packages.txt
collective.ploneseltest.egg-info/not-zip-safe
collective.ploneseltest.egg-info/requires.txt
collective.ploneseltest.egg-info/top_level.txt
collective/ploneseltest/__init__.py
collective/ploneseltest/testcase.py
collective/ploneseltest/tests/__init__.py
collective/ploneseltest/tests/test_example.py
docs/HISTORY.txt
docs/INSTALL.txt
docs/LICENSE.GPL
docs/LICENSE.txt