Metadata-Version: 1.0
Name: collective.ploneseltest
Version: 1.0b2
Summary: Selenium test support for Plone
Home-page: http://plone.org
Author: Martin Aspeli
Author-email: optilude@gmail.com
License: LGPL
Platform: UNKNOWN
Classifier: Framework :: Plone
Classifier: Programming Language :: Python
Classifier: Topic :: Software Development :: Libraries :: Python Modules
